[
    {
        "id": "f434aa5f-1ab7-4970-b63d-a9cb9d373edc",
        "title": "Light Breaker",
        "description": "Light Breaker is a fun mobile game made for android devices. \nI worked in the game as a freelance programmer since the beginning of the project. ",
        "type": "Mobile Application",
        "year": "2021",
        "link": "https://play.google.com/store/apps/details?id=org.godotengine.lightspeedsource",
        "tools": [
            "Godot",
            "OpenGL"
        ],
        "images": [
            "93efab98-4924-46b1-9d73-13c427048593.webp",
            "58a28a76-1483-49c7-adad-90e7bafd509a.webp",
            "fa4b9d99-b990-4e8e-b9e8-f5956437bb99.webp",
            "b504592a-07cc-4b66-bec8-d162fc39fa10.png",
            "e788aaa2-c6e5-4df7-829b-3059fe412ae8.png"
        ],
        "main": 4
    },
    {
        "id": "a87c5317-604b-4486-a389-1ad63e1246b5",
        "title": "SUPER MARIO MANIA",
        "description": "This game is a remake for the most iconic levels in the Super Mario franchise.\n\n\nControls:\n\nMove: arrow keys / gamepad( joystic)k\n\nAccept: space bar / gamepad (A)\n\nPause: enter / gamepad (start)\n\nJump: spacebar / gamepad (A)\n\nThrow Cappy: Q/ gamepad (X)\n\nSprint: S/ gamepad (L2)\n\nDive: D/ gamepad (R2)\n\n",
        "type": "Desktop Application",
        "year": "2020",
        "link": "https://simple-team.itch.io/super-mario-mania",
        "tools": [
            "Godot",
            "OpenGL"
        ],
        "images": [
            "e995179d-8621-4fed-81c8-f803ca03025c.gif",
            "0f277a61-4f4e-4337-b3f1-9f55e9df6e44.gif",
            "ed6d9065-4fd2-436e-94f1-f5230f481efa.gif",
            "3058ca68-2959-4287-8a46-08eae0bef45f.gif",
            "363ed1c5-123d-4eb5-b78e-fbede46494ec.png"
        ],
        "main": 4
    },
    {
        "id": "8a0fa086-bb07-4ce6-bebe-de239f518008",
        "title": "My Porfolio",
        "description": "This portfolio contains all the informations you need regarding my skills, freelance experiences and projects. \nIt was built using HTML, CSS, JavaSript and VueJS.",
        "type": "WEB Application",
        "year": "2022",
        "link": "https://mohamedhaitamksiks.github.io/",
        "tools": [
            "HTML",
            "CSS",
            "JS",
            "VueJS"
        ],
        "images": [
            "4394cc53-f52d-4add-9627-029cd6c4a2d2.png",
            "0a324df5-4a36-4ed8-90e5-cc797bdc62ec.png",
            "42a37df2-b781-4981-a89c-f19dea40ec8a.png",
            "8c75a958-9d30-4d47-a6f6-1866bc8bcca6.gif"
        ],
        "main": 3
    },
    {
        "id": "d7386291-8ebf-40ca-a448-c80f9233e353",
        "title": "Portfolio Projects Manager",
        "description": "It's a desktop application that allows me to add, delete or modify projects for my portfolio.\nIt generates a JSON file that contains all projects. And an Image folder that contains all the projects images.",
        "type": "Desktop Application",
        "year": "2022",
        "link": "https://github.com/MohamedHaitamKsiks/portfolio-projects-manager",
        "tools": [
            "JS",
            "HTML",
            "CSS",
            "VueJS",
            "Bootstrap"
        ],
        "images": [
            "07738007-3881-4358-a0bd-3952a4c1baba.png",
            "ecaf4bd1-429e-480d-a286-7675259277c3.png"
        ],
        "main": 0
    },
    {
        "id": "fd526b37-05cf-4e5a-8823-37466b02be9e",
        "title": "Yui-chan loves her chicken",
        "description": "Explore this abandoned site with Yui-chan and her cute chicken. Fight monsters and boss to level up your health and stamina. Yui-chan can't attack while carrying her chicken, so make sure to put it down to fight. But watch out, monsters target the chicken so protect it, because Yui-chan and her chicken share the same HP.\n\nThis Game was made for the GMTK Game Jam 2021",
        "type": "Desktop Application",
        "year": "2021",
        "link": "https://simple-team.itch.io/yui-loves-her-chicken",
        "tools": [
            "Godot",
            "OpenGL"
        ],
        "images": [
            "e9c7de56-7b97-431a-90e9-aa184c004887.png",
            "bdee3e06-fb89-45b5-a432-f7be23e968f4.png",
            "a3ceabb2-6cdb-4927-9ec8-9464904b149f.png",
            "0bbc90b9-2817-47c1-970f-4280d7938832.gif"
        ],
        "main": 0
    },
    {
        "id": "c3b2bc4b-9fc2-444f-93ea-13727c86b4a9",
        "title": "I did NOT want that card!",
        "description": "In this rogue like , you can't choose your equipment, In fact it's picked randomly form a deck of cards.\n\nThis game was made for the GMTK Game jam 2020",
        "type": "Desktop Application",
        "year": "2020",
        "link": "https://simple-team.itch.io/i-did-not-want-that-card",
        "tools": [
            "Godot",
            "OpenGL"
        ],
        "images": [
            "1e7c9a10-7e41-4a05-9019-38fa0cfb31cb.png",
            "a10547d6-e508-4368-b3e0-769888752f37.png",
            "cfa945cd-5a88-470f-a525-6ab83957692b.png",
            "dd0301d9-af33-4173-a0c0-fd5859c1e3f7.gif"
        ],
        "main": 0
    },
    {
        "id": "c11b1d5e-d162-4e1f-8c3d-f927f694206f",
        "title": "Law Firm Manager",
        "description": "A Law firm manager created to make it easy for lawyers to organize their cases, It was made as an end of year school project.",
        "type": "WEB Application",
        "year": "2022",
        "link": "https://github.com/MohamedHaitamKsiks/PFA_1A",
        "tools": [
            "HTML",
            "CSS",
            "VueJS",
            "ExpressJS"
        ],
        "images": [
            "ef099837-d64b-496f-9867-24794fc4d7f4.png",
            "94dad9b2-a73a-42f5-9e3b-5cbfee6c0a55.png",
            "65a2482c-b567-44ce-8586-efac4512a0c1.png",
            "81e0f610-7b02-4794-bbd4-6fc4cf048b91.png"
        ],
        "main": 2
    },
    {
        "id": "0c648756-8c9f-4683-a224-4ebe7b322b92",
        "title": "Algorithm Interpreted",
        "description": "An interpreter and text-editor for a programming language that I made. It's inspired by the way we write pseudo-code in french.",
        "type": "Desktop Application",
        "year": "2019",
        "link": "https://github.com/MohamedHaitamKsiks/AlgorithmInterpreter",
        "tools": [
            "Python"
        ],
        "images": [
            "f6a9fe56-87e0-46ab-9904-eebbded0c9e5.png",
            "876b2443-8b00-4018-a998-859aa6cbba8c.png",
            "094606ff-4ca2-4dfb-9ebb-07b8f5575e64.png"
        ],
        "main": 1
    },
    {
        "id": "b2f32af2-8633-40d2-a7e1-ee740fa2694b",
        "title": "Hallow Queen (WIP)",
        "description": "A small game I'm working on as a freelancer Godot developer and artist with fodderlabs.\nIt's a game where you have to fight multiple bosses to progress.\n\nThe game is still in development, only the demo is available to the public.",
        "type": "Desktop Application",
        "year": "2023",
        "link": "https://fodderlabs.itch.io/hallowqueen",
        "tools": [
            "Godot",
            "OpenGL"
        ],
        "images": [
            "5f2bb671-88b4-4c45-9b96-e126e83f806a.gif",
            "a463a6d9-b0c0-4bff-8a43-39f085ba987e.png",
            "41fdec0b-86bb-43b1-811d-69ce8f19f1dc.png",
            "35b950a2-106e-4e0d-a4c4-ed0295584986.png",
            "4f862347-a8bf-407d-89ff-720c5dd76097.png",
            "d1d7d98e-4afe-44bb-89de-4aac22cb8a34.png",
            "175f9560-9af5-417a-8c07-5bca3e3418e7.png",
            "8861ca0d-2eac-44ad-9f02-e6dfdfe93949.gif"
        ],
        "main": 7
    },
    {
        "id": "e058ae94-b79f-4033-92d0-18fc380d0e52",
        "title": "Luck Thief",
        "description": "A small game I made for the 48 hours GMTK game jam of 2022.",
        "type": "Desktop Application",
        "year": "2022",
        "link": "https://simple-team.itch.io/luck-thief",
        "tools": [
            "Godot",
            "OpenGL"
        ],
        "images": [
            "e0e54427-3ff2-48f9-85d3-19d75116ed02.png",
            "5267f07c-b484-4085-9d6b-0f529c9e0a56.png",
            "4d9a1e4f-768c-4e95-94b1-aaa2011f946b.png",
            "aa6c79ea-0881-4303-ac28-d25b08509404.png"
        ],
        "main": 0
    },
    {
        "id": "1ae46dc2-6d16-47d3-9350-63437c141a18",
        "title": "FodderLabs Portfolio",
        "description": "It's a static website made with vue.js.\nIt's a portfolio that contains all the projects that my client worked/is working on.\nThe website is not online yet.",
        "type": "WEB Application",
        "year": "2023",
        "link": "/",
        "tools": [
            "CSS",
            "HTML",
            "JS",
            "VueJS"
        ],
        "images": [
            "79fe61f3-7060-4bce-9fba-2f9484e64a7d.png",
            "c923890d-182b-40bd-9993-fc762e85467c.png",
            "b5a1d3ad-edb7-4ff2-9032-ccdea9db65ae.png",
            "af526c75-d2fb-485a-9e35-9d45e0ce1696.png",
            "5919d328-270c-4bd0-8560-9769e38df92c.png",
            "24cc7779-83c2-48f1-a444-c0dc9f8fe950.gif"
        ],
        "main": 5
    },
    {
        "id": "95cbb6ba-a86d-4fc7-8bb0-1ea6aa92baab",
        "title": "World Cup Manager (Front end)",
        "description": "This project is a world cup manager made for a school project.\nI was responsible of making the front end of the application.\nThe back end was in Oracle Apex. ",
        "type": "WEB Application",
        "year": "2023",
        "link": "https://github.com/MohamedHaitamKsiks/worldcup-stats-web-application",
        "tools": [
            "HTML",
            "CSS",
            "JS",
            "VueJS"
        ],
        "images": [
            "13f8803d-c064-4f1f-8e10-4f3e65d4de52.png",
            "4bf4fca4-d5d7-44c7-9c92-30b7daf6492a.png",
            "532556b8-7a35-4c34-9ba1-ce94b0c53bbe.png",
            "4448057f-f1aa-4fb0-af09-b55060910d43.png"
        ],
        "main": 3
    },
    {
        "id": "ddcbe4d5-9c70-4ae8-b547-71db5dc37fe7",
        "title": "Kanji Engine (WIP)",
        "description": "Kanji is a free open source game engine I'm making as a personal project to learn more about graphics programming and game engine development.\nThe renderer is built with Vulkan. \nThe engine is still on it's debut.",
        "type": "Desktop Application",
        "year": "2023",
        "link": "https://github.com/MohamedHaitamKsiks/kanji-engine",
        "tools": [
            "C++",
            "Vulkan"
        ],
        "images": [
            "00cf9cd9-3ed8-4f7e-9337-0c0a939eb3b1.gif",
            "35d01407-57a7-46a2-9bb4-231cecbe610c.png"
        ],
        "main": 0
    },
    {
        "id": "6ad50749-8f5e-4484-8c53-3375a644d3a5",
        "title": "Android Simple Engine (WIP)",
        "description": "Android game engine written with native c++ and android studio.\nThe engine was made to help create a mobile game for a school project.\nThe engine has :\n1. Resource management (sprites, fonts, materials ..)\n2. 2D Renderer with OpenGL ES 2.0\n3. Input Management\n4. Game Objects\n5. Particle System\n\nOther features are coming soon.",
        "type": "Mobile Application",
        "year": "2023",
        "link": "https://github.com/MohamedHaitamKsiks/android_simple_engine",
        "tools": [
            "Android Studio",
            "C++",
            "OpenGL ES"
        ],
        "images": [
            "628eb31c-a02e-49a9-9d85-5efebc770a93.gif"
        ],
        "main": 0
    },
    {
        "id": "b9e46404-438c-49a1-b923-8048247855f7",
        "title": "Resource Manger",
        "description": "It's a fullstack web application made in my first year internship at HAGOUNIA BTP.\nIt helps the company to manage its resources.",
        "type": "WEB Application",
        "year": "2022",
        "link": "/",
        "tools": [
            "HTML",
            "CSS",
            "JS",
            "VueJS",
            "NodeJS",
            "ExpressJS"
        ],
        "images": [
            "49174739-3f2a-4197-a67b-15264108683c.png",
            "98bcc1c1-ba31-4213-9452-44d5861e7889.png",
            "fb0452b6-5784-4385-b110-cab3f3d8ae76.png",
            "18abfde2-3d18-451a-9275-39dfccf367c9.png",
            "5871902b-0d3e-4509-8468-9dcaf787b45a.png",
            "807056be-5471-4cc0-9f53-2dbf86297ccb.png",
            "7dfde1d1-0acd-4464-9671-d6ab1958a3bb.png",
            "2cf7eb09-8a46-4351-b26e-96f9e178f234.png",
            "6d1e6a48-a0f8-446a-920f-6b3329950f32.png"
        ],
        "main": 0
    }
]